tlspy/__init__.py
tlspy-0.0.1.dist-info/METADATA
tlspy-0.0.1.dist-info/WHEEL
tlspy-0.0.1.dist-info/licenses/LICENSE
tlspy-0.0.1.dist-info/RECORD
